{"identifier":{"url":"doc:\/\/com.mimik.EdgeCore\/documentation\/EdgeCore\/EdgeCore","interfaceLanguage":"swift"},"schemaVersion":{"patch":0,"major":0,"minor":3},"variants":[{"traits":[{"interfaceLanguage":"swift"}],"paths":["\/documentation\/edgecore\/edgecore"]}],"abstract":[{"text":"The ","type":"text"},{"type":"strong","inlineContent":[{"text":"mimik Client Library","type":"text"}]},{"text":" is a unified SDK for integrating and managing ","type":"text"},{"type":"strong","inlineContent":[{"text":"mimik OE","type":"text"}]},{"text":" — a lightweight mimik operating environment enabling developers to build, deploy, and orchestrate microservices and AI-powered workflows across hybrid edge-cloud systems.","type":"text"}],"kind":"article","hierarchy":{"paths":[["doc:\/\/com.mimik.EdgeCore\/documentation\/EdgeCore"]]},"primaryContentSections":[{"kind":"content","content":[{"anchor":"overview","level":2,"text":"Overview","type":"heading"},{"type":"paragraph","inlineContent":[{"text":"It abstracts away the complexities of:","type":"text"}]},{"items":[{"content":[{"inlineContent":[{"text":"OAuth2 \/ JWT-based authentication","type":"text"}],"type":"paragraph"}]},{"content":[{"type":"paragraph","inlineContent":[{"text":"Network node discovery and orchestration","type":"text"}]}]},{"content":[{"type":"paragraph","inlineContent":[{"type":"text","text":"Lifecycle and configuration management for microservices"}]}]},{"content":[{"inlineContent":[{"text":"AI model integration, unified assistant streaming prompts","type":"text"}],"type":"paragraph"}]}],"type":"unorderedList"},{"type":"thematicBreak"},{"anchor":"%F0%9F%9A%80-Getting-Started","level":2,"text":"🚀 Getting Started","type":"heading"},{"type":"paragraph","inlineContent":[{"type":"text","text":"The fastest way to get started:"}]},{"items":[{"content":[{"type":"paragraph","inlineContent":[{"type":"text","text":"Follow the onboarding tutorial"},{"type":"text","text":"\n"},{"type":"text","text":"📘 "},{"type":"reference","isActive":true,"identifier":"https:\/\/devdocs.mimik.com\/tutorials\/01-submenu\/02-submenu\/02-index"}]}]},{"content":[{"type":"paragraph","inlineContent":[{"type":"text","text":"Add the required pods to your "},{"code":"Podfile","type":"codeVoice"},{"type":"text","text":":"}]},{"type":"codeListing","syntax":"ruby","code":["platform :ios, '16.0'","source 'https:\/\/github.com\/CocoaPods\/Specs.git'","source 'https:\/\/github.com\/mimikgit\/cocoapod-edge-specs.git'","","use_frameworks!","inhibit_all_warnings!","","def mimik","  pod 'EdgeCore'","  pod 'mim-OE-ai-SE-iOS-developer'","end","","target 'YourAppTarget' do","  mimik()","end","","post_install do |installer|","  installer.pods_project.targets.each do |target|","    target.build_configurations.each do |config|","      config.build_settings['VALID_ARCHS'] = '$(ARCHS_STANDARD_64_BIT)'","      config.build_settings['IPHONEOS_DEPLOYMENT_TARGET'] = '16.0'","      config.build_settings['BUILD_LIBRARY_FOR_DISTRIBUTION'] = 'YES'","    end","  end","end"]}]},{"content":[{"type":"paragraph","inlineContent":[{"type":"text","text":"Get your mim OE license key from the "},{"isActive":true,"identifier":"https:\/\/developer.mimik.com\/console","type":"reference"}]}]}],"type":"orderedList"},{"type":"thematicBreak"},{"anchor":"%F0%9F%92%A1-Key-Concepts","level":2,"text":"💡 Key Concepts","type":"heading"},{"type":"paragraph","inlineContent":[{"inlineContent":[{"type":"text","text":"mim OE"}],"type":"strong"},{"text":" (Operating Environment) is the runtime platform powering edge microservices and AI workloads. It can run on iOS devices, simulators, or macOS using Catalyst. The Client Library gives you direct control over:","type":"text"}]},{"items":[{"content":[{"type":"paragraph","inlineContent":[{"type":"text","text":"Service deployment"}]}]},{"content":[{"type":"paragraph","inlineContent":[{"text":"Runtime lifecycle","type":"text"}]}]},{"content":[{"type":"paragraph","inlineContent":[{"type":"text","text":"AI model execution"}]}]},{"content":[{"type":"paragraph","inlineContent":[{"type":"text","text":"Secure communication and auth"}]}]}],"type":"unorderedList"},{"type":"thematicBreak"},{"anchor":"%E2%9C%A8-Features-Overview","level":2,"text":"✨ Features Overview","type":"heading"},{"type":"paragraph","inlineContent":[{"text":"The mimik Client Library provides a unified API to:","type":"text"}]},{"anchor":"%F0%9F%94%A7-Initialize-and-Control-mim-OE","level":3,"text":"🔧 Initialize and Control mim OE","type":"heading"},{"items":[{"content":[{"type":"paragraph","inlineContent":[{"type":"text","text":"Start, stop, and monitor the mim OE runtime"}]}]},{"content":[{"type":"paragraph","inlineContent":[{"type":"text","text":"Configure logging, runtime health, and startup parameters"}]}]}],"type":"unorderedList"},{"anchor":"%F0%9F%94%90-Authenticate-Developers-and-Users","level":3,"text":"🔐 Authenticate Developers and Users","type":"heading"},{"items":[{"content":[{"type":"paragraph","inlineContent":[{"text":"OAuth2-compliant developer and user login","type":"text"}]}]},{"content":[{"type":"paragraph","inlineContent":[{"type":"text","text":"Support for token exchange, scopes, signup\/login flows"}]}]},{"content":[{"inlineContent":[{"text":"Handle account recovery, password changes, and deletions","type":"text"}],"type":"paragraph"}]}],"type":"unorderedList"},{"anchor":"%F0%9F%8C%8D-Discover--Orchestrate-Edge-Nodes","level":3,"text":"🌍 Discover & Orchestrate Edge Nodes","type":"heading"},{"items":[{"content":[{"type":"paragraph","inlineContent":[{"text":"Auto-discover available edge nodes","type":"text"}]}]},{"content":[{"type":"paragraph","inlineContent":[{"type":"text","text":"Route requests across hybrid clusters"}]}]},{"content":[{"type":"paragraph","inlineContent":[{"text":"Register and manage services","type":"text"}]}]}],"type":"unorderedList"},{"anchor":"%F0%9F%93%A6-Deploy--Manage-Microservices","level":3,"text":"📦 Deploy & Manage Microservices","type":"heading"},{"items":[{"content":[{"inlineContent":[{"text":"Deploy microservices or full use-case workflows","type":"text"}],"type":"paragraph"}]},{"content":[{"inlineContent":[{"text":"Package using container-style config and update dynamically","type":"text"}],"type":"paragraph"}]},{"content":[{"inlineContent":[{"type":"text","text":"Scale, tear down, or update services via API"}],"type":"paragraph"}]}],"type":"unorderedList"},{"anchor":"%F0%9F%A4%96-Unified-AI-Model-Integration","level":3,"text":"🤖 Unified AI Model Integration","type":"heading"},{"items":[{"content":[{"type":"paragraph","inlineContent":[{"text":"List available AI models across device, edge, and cloud","type":"text"}]}]},{"content":[{"inlineContent":[{"text":"Use a single interface to prompt vision and language models","type":"text"}],"type":"paragraph"}]}],"type":"unorderedList"},{"anchor":"%F0%9F%94%81-Stream-AI-Prompts--Responses","level":3,"text":"🔁 Stream AI Prompts & Responses","type":"heading"},{"items":[{"content":[{"type":"paragraph","inlineContent":[{"type":"text","text":"Send prompts and receive streaming replies"}]}]},{"content":[{"type":"paragraph","inlineContent":[{"text":"Handle user-initiated prompt cancellations cleanly","type":"text"}]}]}],"type":"unorderedList"},{"anchor":"%F0%9F%93%8B-Standardized-AI-Outputs","level":3,"text":"📋 Standardized AI Outputs","type":"heading"},{"items":[{"content":[{"inlineContent":[{"type":"text","text":"Unified output handling via "},{"code":"AssistantOutput","type":"codeVoice"}],"type":"paragraph"}]},{"content":[{"type":"paragraph","inlineContent":[{"text":"Supports chat UI, system automation, and batch processing","type":"text"}]}]}],"type":"unorderedList"},{"type":"thematicBreak"},{"anchor":"%F0%9F%93%A6-Pod-Distribution","level":2,"text":"📦 Pod Distribution","type":"heading"},{"type":"paragraph","inlineContent":[{"text":"Use the table below to choose the CocoaPods that best match your use case:","type":"text"}]},{"header":"row","type":"table","rows":[[[{"type":"paragraph","inlineContent":[{"text":"Pod","type":"text"}]}],[{"type":"paragraph","inlineContent":[{"type":"text","text":"Includes"}]}],[{"type":"paragraph","inlineContent":[{"type":"text","text":"AI Support"}]}],[{"type":"paragraph","inlineContent":[{"text":"Recommended For","type":"text"}]}]],[[{"type":"paragraph","inlineContent":[{"identifier":"https:\/\/github.com\/mimikgit\/cocoapod-EdgeCore","isActive":true,"type":"reference"}]}],[{"type":"paragraph","inlineContent":[{"type":"text","text":"Core"}]}],[{"type":"paragraph","inlineContent":[]}],[{"type":"paragraph","inlineContent":[{"type":"text","text":"Always include"}]}]],[[{"type":"paragraph","inlineContent":[{"isActive":true,"identifier":"https:\/\/github.com\/mimikgit\/cocoapod-mim-OE-SE-iOS-developer","type":"reference"}]}],[{"type":"paragraph","inlineContent":[{"type":"text","text":"Core + mim OE"}]}],[{"type":"paragraph","inlineContent":[{"type":"text","text":"❌"}]}],[{"type":"paragraph","inlineContent":[{"type":"text","text":"Lightweight, non-AI apps"}]}]],[[{"type":"paragraph","inlineContent":[{"identifier":"https:\/\/github.com\/mimikgit\/cocoapod-mim-OE-ai-SE-iOS-developer","isActive":true,"type":"reference"}]}],[{"type":"paragraph","inlineContent":[{"text":"Core + mim OE + AI","type":"text"}]}],[{"type":"paragraph","inlineContent":[{"type":"text","text":"✅"}]}],[{"type":"paragraph","inlineContent":[{"type":"text","text":"Vision\/Language AI support"}]}]],[[{"type":"paragraph","inlineContent":[{"identifier":"https:\/\/github.com\/mimikgit\/cocoapod-EdgeService","isActive":true,"type":"reference"}]}],[{"type":"paragraph","inlineContent":[{"type":"text","text":"Deployment tools"}]}],[{"type":"paragraph","inlineContent":[]}],[{"type":"paragraph","inlineContent":[{"text":"For managing custom microservices","type":"text"}]}]]]},{"style":"note","content":[{"type":"paragraph","inlineContent":[{"inlineContent":[{"type":"text","text":"✅ Recommended Default:"}],"type":"strong"},{"text":" Add ","type":"text"},{"code":"EdgeCore","type":"codeVoice"},{"text":" and ","type":"text"},{"code":"mim-OE-ai-SE-iOS-developer","type":"codeVoice"},{"text":" to your Podfile.","type":"text"}]}],"name":"Note","type":"aside"},{"type":"thematicBreak"},{"anchor":"%F0%9F%93%B1-Supported-Platforms","level":2,"text":"📱 Supported Platforms","type":"heading"},{"items":[{"content":[{"inlineContent":[{"type":"strong","inlineContent":[{"text":"iOS Devices:","type":"text"}]},{"text":" iOS 16.0+","type":"text"}],"type":"paragraph"}]},{"content":[{"type":"paragraph","inlineContent":[{"type":"strong","inlineContent":[{"type":"text","text":"iOS Simulators:"}]},{"type":"text","text":" iOS 16.0+"}]}]},{"content":[{"inlineContent":[{"type":"strong","inlineContent":[{"text":"Mac Catalyst:","type":"text"}]},{"type":"text","text":" macOS 14.0+"}],"type":"paragraph"}]}],"type":"unorderedList"},{"type":"thematicBreak"},{"anchor":"%F0%9F%93%84-Documentation","level":2,"text":"📄 Documentation","type":"heading"},{"items":[{"content":[{"type":"paragraph","inlineContent":[{"type":"strong","inlineContent":[{"type":"text","text":"API Reference (EdgeCore):"}]},{"type":"text","text":""},{"type":"text","text":"\n"},{"identifier":"https:\/\/mimikgit.github.io\/cocoapod-EdgeCore\/documentation\/edgecore\/edgeclient","type":"reference","isActive":true},{"type":"text","text":""},{"type":"text","text":"\n"},{"identifier":"https:\/\/mimikgit.github.io\/cocoapod-EdgeCore\/documentation\/edgecore\/edgeengineclient","type":"reference","isActive":true}]}]},{"content":[{"type":"paragraph","inlineContent":[{"type":"strong","inlineContent":[{"text":"EdgeService Reference:","type":"text"}]},{"text":"","type":"text"},{"text":"\n","type":"text"},{"isActive":true,"identifier":"https:\/\/mimikgit.github.io\/cocoapod-EdgeService\/documentation\/edgeservice","type":"reference"}]}]},{"content":[{"type":"paragraph","inlineContent":[{"type":"text","text":"All APIs are also documented in Xcode with built-in method and struct descriptions."}]}]}],"type":"unorderedList"},{"type":"thematicBreak"},{"anchor":"%F0%9F%A7%AA-Tutorials-by-Use-Case","level":2,"text":"🧪 Tutorials by Use Case","type":"heading"},{"anchor":"%E2%96%B6%EF%B8%8F-Get-Started","level":3,"text":"▶️ Get Started","type":"heading"},{"items":[{"content":[{"type":"paragraph","inlineContent":[{"identifier":"https:\/\/devdocs.mimik.com\/key-concepts\/10-index","isActive":true,"type":"reference"}]}]}],"type":"unorderedList"},{"anchor":"%F0%9F%9B%A0%EF%B8%8F-Build-Apps","level":3,"text":"🛠️ Build Apps","type":"heading"},{"items":[{"content":[{"inlineContent":[{"type":"reference","isActive":true,"identifier":"https:\/\/devdocs.mimik.com\/tutorials\/01-submenu\/02-submenu\/01-index"}],"type":"paragraph"}]},{"content":[{"type":"paragraph","inlineContent":[{"identifier":"https:\/\/devdocs.mimik.com\/tutorials\/01-submenu\/02-submenu\/02-index","type":"reference","isActive":true,"overridingTitleInlineContent":[{"type":"text","text":"Integrating the mimik Client Library into Your iOS Project"}],"overridingTitle":"Integrating the mimik Client Library into Your iOS Project"}]}]}],"type":"unorderedList"},{"anchor":"%E2%9A%99%EF%B8%8F-Work-with-Runtime","level":3,"text":"⚙️ Work with Runtime","type":"heading"},{"items":[{"content":[{"inlineContent":[{"type":"reference","identifier":"https:\/\/devdocs.mimik.com\/tutorials\/01-submenu\/02-submenu\/03-index","isActive":true}],"type":"paragraph"}]}],"type":"unorderedList"},{"anchor":"%F0%9F%93%A6-Manage-Microservices","level":3,"text":"📦 Manage Microservices","type":"heading"},{"items":[{"content":[{"inlineContent":[{"type":"reference","identifier":"https:\/\/devdocs.mimik.com\/tutorials\/01-submenu\/02-submenu\/04-index","isActive":true}],"type":"paragraph"}]}],"type":"unorderedList"},{"type":"thematicBreak"},{"anchor":"%F0%9F%93%9C-Licensing","level":2,"text":"📜 Licensing","type":"heading"},{"type":"paragraph","inlineContent":[{"text":"To initialize ","type":"text"},{"code":"mim-OE-ai-SE-iOS-developer","type":"codeVoice"},{"text":", obtain a license key at:","type":"text"},{"text":"\n","type":"text"},{"text":"🔐 ","type":"text"},{"overridingTitle":"mimik Developer Console","identifier":"https:\/\/developer.mimik.com\/console","overridingTitleInlineContent":[{"type":"text","text":"mimik Developer Console"}],"isActive":true,"type":"reference"}]},{"type":"paragraph","inlineContent":[{"type":"text","text":"For enterprise projects or commercial distribution, contact:"},{"type":"text","text":"\n"},{"type":"text","text":"💼 "},{"type":"reference","identifier":"https:\/\/mimik.com\/contact-us\/","isActive":true}]},{"type":"thematicBreak"},{"anchor":"%F0%9F%91%A4-Author","level":2,"text":"👤 Author","type":"heading"},{"type":"paragraph","inlineContent":[{"identifier":"https:\/\/mimik.com","isActive":true,"type":"reference"},{"text":"","type":"text"},{"text":"\n","type":"text"},{"text":"Learn more at ","type":"text"},{"identifier":"https:\/\/devdocs.mimik.com","isActive":true,"type":"reference"}]}]}],"sections":[],"metadata":{"modules":[{"name":"EdgeCore"}],"roleHeading":"Article","role":"article","title":"mimik Client Library"},"references":{"https://mimikgit.github.io/cocoapod-EdgeCore/documentation/edgecore/edgeengineclient":{"identifier":"https:\/\/mimikgit.github.io\/cocoapod-EdgeCore\/documentation\/edgecore\/edgeengineclient","url":"https:\/\/mimikgit.github.io\/cocoapod-EdgeCore\/documentation\/edgecore\/edgeengineclient","title":"EdgeEngineClient Protocol","type":"link","titleInlineContent":[{"text":"EdgeEngineClient Protocol","type":"text"}]},"https://devdocs.mimik.com/tutorials/01-submenu/02-submenu/04-index":{"identifier":"https:\/\/devdocs.mimik.com\/tutorials\/01-submenu\/02-submenu\/04-index","title":"Deploying Edge Microservices","type":"link","url":"https:\/\/devdocs.mimik.com\/tutorials\/01-submenu\/02-submenu\/04-index","titleInlineContent":[{"text":"Deploying Edge Microservices","type":"text"}]},"https://github.com/mimikgit/cocoapod-mim-OE-ai-SE-iOS-developer":{"identifier":"https:\/\/github.com\/mimikgit\/cocoapod-mim-OE-ai-SE-iOS-developer","url":"https:\/\/github.com\/mimikgit\/cocoapod-mim-OE-ai-SE-iOS-developer","title":"mim-OE-ai-SE-iOS-developer","type":"link","titleInlineContent":[{"code":"mim-OE-ai-SE-iOS-developer","type":"codeVoice"}]},"https://developer.mimik.com/console":{"identifier":"https:\/\/developer.mimik.com\/console","title":"mimik Developer Console","type":"link","url":"https:\/\/developer.mimik.com\/console","titleInlineContent":[{"text":"mimik Developer Console","type":"text"}]},"https://devdocs.mimik.com/key-concepts/10-index":{"identifier":"https:\/\/devdocs.mimik.com\/key-concepts\/10-index","url":"https:\/\/devdocs.mimik.com\/key-concepts\/10-index","title":"Understanding the mimik Client Library for iOS","type":"link","titleInlineContent":[{"text":"Understanding the mimik Client Library for iOS","type":"text"}]},"doc://com.mimik.EdgeCore/documentation/EdgeCore":{"role":"collection","identifier":"doc:\/\/com.mimik.EdgeCore\/documentation\/EdgeCore","kind":"symbol","type":"topic","abstract":[],"title":"EdgeCore","url":"\/documentation\/edgecore"},"https://github.com/mimikgit/cocoapod-EdgeService":{"identifier":"https:\/\/github.com\/mimikgit\/cocoapod-EdgeService","title":"EdgeService","type":"link","url":"https:\/\/github.com\/mimikgit\/cocoapod-EdgeService","titleInlineContent":[{"code":"EdgeService","type":"codeVoice"}]},"https://devdocs.mimik.com/tutorials/01-submenu/02-submenu/02-index":{"identifier":"https:\/\/devdocs.mimik.com\/tutorials\/01-submenu\/02-submenu\/02-index","url":"https:\/\/devdocs.mimik.com\/tutorials\/01-submenu\/02-submenu\/02-index","title":"Step-by-Step Tutorial","type":"link","titleInlineContent":[{"text":"Step-by-Step Tutorial","type":"text"}]},"https://mimikgit.github.io/cocoapod-EdgeCore/documentation/edgecore/edgeclient":{"identifier":"https:\/\/mimikgit.github.io\/cocoapod-EdgeCore\/documentation\/edgecore\/edgeclient","title":"EdgeClient Reference","type":"link","url":"https:\/\/mimikgit.github.io\/cocoapod-EdgeCore\/documentation\/edgecore\/edgeclient","titleInlineContent":[{"text":"EdgeClient Reference","type":"text"}]},"https://devdocs.mimik.com/tutorials/01-submenu/02-submenu/01-index":{"identifier":"https:\/\/devdocs.mimik.com\/tutorials\/01-submenu\/02-submenu\/01-index","url":"https:\/\/devdocs.mimik.com\/tutorials\/01-submenu\/02-submenu\/01-index","title":"Creating a Simple iOS App Using an Edge Microservice","type":"link","titleInlineContent":[{"text":"Creating a Simple iOS App Using an Edge Microservice","type":"text"}]},"https://devdocs.mimik.com/tutorials/01-submenu/02-submenu/03-index":{"identifier":"https:\/\/devdocs.mimik.com\/tutorials\/01-submenu\/02-submenu\/03-index","title":"Working with mim OE in an iOS Project","type":"link","url":"https:\/\/devdocs.mimik.com\/tutorials\/01-submenu\/02-submenu\/03-index","titleInlineContent":[{"text":"Working with mim OE in an iOS Project","type":"text"}]},"https://devdocs.mimik.com":{"identifier":"https:\/\/devdocs.mimik.com","url":"https:\/\/devdocs.mimik.com","title":"mimik Developer Documentation","type":"link","titleInlineContent":[{"text":"mimik Developer Documentation","type":"text"}]},"https://github.com/mimikgit/cocoapod-EdgeCore":{"identifier":"https:\/\/github.com\/mimikgit\/cocoapod-EdgeCore","title":"EdgeCore","type":"link","url":"https:\/\/github.com\/mimikgit\/cocoapod-EdgeCore","titleInlineContent":[{"code":"EdgeCore","type":"codeVoice"}]},"https://github.com/mimikgit/cocoapod-mim-OE-SE-iOS-developer":{"identifier":"https:\/\/github.com\/mimikgit\/cocoapod-mim-OE-SE-iOS-developer","url":"https:\/\/github.com\/mimikgit\/cocoapod-mim-OE-SE-iOS-developer","title":"mim-OE-SE-iOS-developer","type":"link","titleInlineContent":[{"code":"mim-OE-SE-iOS-developer","type":"codeVoice"}]},"https://mimik.com/contact-us/":{"identifier":"https:\/\/mimik.com\/contact-us\/","title":"mimik Support","type":"link","url":"https:\/\/mimik.com\/contact-us\/","titleInlineContent":[{"text":"mimik Support","type":"text"}]},"https://mimikgit.github.io/cocoapod-EdgeService/documentation/edgeservice":{"identifier":"https:\/\/mimikgit.github.io\/cocoapod-EdgeService\/documentation\/edgeservice","url":"https:\/\/mimikgit.github.io\/cocoapod-EdgeService\/documentation\/edgeservice","title":"EdgeServiceClient Docs","type":"link","titleInlineContent":[{"text":"EdgeServiceClient Docs","type":"text"}]},"https://mimik.com":{"identifier":"https:\/\/mimik.com","title":"mimik","type":"link","url":"https:\/\/mimik.com","titleInlineContent":[{"text":"mimik","type":"text"}]}}}